SHA-256v1/VHDL/vectorGenerator.vhd
LIBRARY ieee;
USE     ieee.std_logic_1164.ALL;
USE     ieee.numeric_std.ALL;

ENTITY vectorGenerator IS
  PORT (dgst : IN STD_LOGIC_VECTOR (255 DOWNTO 0);
        cts  : IN STD_LOGIC;
        clk  : OUT STD_LOGIC;
        rst  : OUT STD_LOGIC;
        msg  : OUT STD_LOGIC_VECTOR (511 DOWNTO 0));
END vectorGenerator;

ARCHITECTURE behavioral OF vectorGenerator IS

  CONSTANT ckP  : TIME := 10 ns;
  SIGNAL   iClk : STD_LOGIC;
  SIGNAL   iRst : STD_LOGIC := '0';

BEGIN

  feed_msg : PROCESS(cts)
  BEGIN
    IF (cts = '1') THEN --(511 => '1', OTHERS => '0');
      msg <= --x"61626380" &
             x"80000000" &
             x"00000000" &
             x"00000000" &
             x"00000000" &
             x"00000000" &
             x"00000000" &
             x"00000000" &
             x"00000000" &
             x"00000000" &
             x"00000000" &
             x"00000000" &
             x"00000000" &
             x"00000000" &
             x"00000000" &
             x"00000000" &
             x"00000000";
             --x"00000018";
    END IF;
  END PROCESS feed_msg;

  clock   : PROCESS
    VARIABLE clkTmp : STD_LOGIC := '0';
    VARIABLE cnt    : INTEGER   := 0;
  BEGIN
    cnt := cnt +1;
    iClk <= clkTmp;
    clkTmp := NOT clkTmp;

    IF (cnt < 140) THEN
      WAIT FOR ckP * 0.5;
    ELSE
      iRst <= '1';
      WAIT;
    END IF;

  END PROCESS clock;

  clk  <= iClk;
  rst <= iRst;

END behavioral;

SHA-256v1/VHDL/compressor.vhd
LIBRARY ieee;
USE     ieee.std_logic_1164.ALL;
USE     ieee.numeric_std.ALL;

ENTITY compressorSHA256 IS
  PORT    (clk  : IN  STD_LOGIC;                         --clock
           rst  : IN  STD_LOGIC;                         --reset
           enbl : IN  STD_LOGIC;                         --enable
           inp  : IN  STD_LOGIC_VECTOR (31 DOWNTO 0);    --input
           outp : OUT STD_LOGIC_VECTOR (255 DOWNTO 0));  --output
END compressorSHA256;

ARCHITECTURE behavioral OF compressorSHA256 IS

  CONSTANT k_dim    : INTEGER     := 64;                  --dimension of k (in numero di word - 2048 bit)
  CONSTANT word_dim : INTEGER     := 32;                  --word dimension (in numero di bit)
  CONSTANT cycles   : INTEGER     := 64;

  SUBTYPE WORD        IS UNSIGNED (word_dim-1 DOWNTO 0);
  TYPE    CONST_ARRAY IS ARRAY    (0 TO k_dim-1) OF WORD;

  CONSTANT k        : CONST_ARRAY := (x"428a2f98", x"71374491", x"b5c0fbcf", x"e9b5dba5", x"3956c25b", x"59f111f1", x"923f82a4", x"ab1c5ed5",
                                      x"d807aa98", x"12835b01", x"243185be", x"550c7dc3", x"72be5d74", x"80deb1fe", x"9bdc06a7", x"c19bf174",
                                      x"e49b69c1", x"efbe4786", x"0fc19dc6", x"240ca1cc", x"2de92c6f", x"4a7484aa", x"5cb0a9dc", x"76f988da",
                                      x"983e5152", x"a831c66d", x"b00327c8", x"bf597fc7", x"c6e00bf3", x"d5a79147", x"06ca6351", x"14292967",
                                      x"27b70a85", x"2e1b2138", x"4d2c6dfc", x"53380d13", x"650a7354", x"766a0abb", x"81c2c92e", x"92722c85",
                                      x"a2bfe8a1", x"a81a664b", x"c24b8b70", x"c76c51a3", x"d192e819", x"d6990624", x"f40e3585", x"106aa070",
                                      x"19a4c116", x"1e376c08", x"2748774c", x"34b0bcb5", x"391c0cb3", x"4ed8aa4a", x"5b9cca4f", x"682e6ff3",
                                      x"748f82ee", x"78a5636f", x"84c87814", x"8cc70208", x"90befffa", x"a4506ceb", x"bef9a3f7", x"c67178f2");

  SIGNAL cnt        : INTEGER     := 0;        --contatore

  SIGNAL h0, a      : WORD        :=  x"6a09e667";
  SIGNAL h1, b      : WORD        :=  x"bb67ae85";
  SIGNAL h2, c      : WORD        :=  x"3c6ef372";
  SIGNAL h3, d      : WORD        :=  x"a54ff53a";
  SIGNAL h4, e      : WORD        :=  x"510e527f";
  SIGNAL h5, f      : WORD        :=  x"9b05688c";
  SIGNAL h6, g      : WORD        :=  x"1f83d9ab";
  SIGNAL h7, h      : WORD        :=  x"5be0cd19";

  SIGNAL s0, s1     : WORD;
  SIGNAL maj        : WORD;
  SIGNAL t1n, t2     : WORD;
  SIGNAL ch         : WORD;

  SIGNAL rr02, rr06 : WORD;
  SIGNAL rr11, rr13 : WORD;
  SIGNAL rr22, rr25 : WORD;

BEGIN

  PROCESS (rst, clk)
    --VARIABLE cnt : INTEGER := 0;
  BEGIN
    IF (rst = '1') THEN
      cnt <= 0;
      h0  <= x"6a09e667";  a <= x"6a09e667";
      h1  <= x"bb67ae85";  b <= x"bb67ae85";
      h2  <= x"3c6ef372";  c <= x"3c6ef372";
      h3  <= x"a54ff53a";  d <= x"a54ff53a";
      h4  <= x"510e527f";  e <= x"510e527f";
      h5  <= x"9b05688c";  f <= x"9b05688c";
      h6  <= x"1f83d9ab";  g <= x"1f83d9ab";
      h7  <= x"5be0cd19";  h <= x"5be0cd19";
    END IF;
    
    IF (clk'EVENT AND clk = '1') THEN

      IF (enbl = '1') THEN
        IF (cnt < cycles) THEN
          cnt <= cnt + 1;
          h   <= g;
          g   <= f;
          f   <= e;
          e   <= d + t1n + UNSIGNED(inp) + k(cnt);
          d   <= c;
          c   <= b;
          b   <= a;
          a   <= t1n + t2 + UNSIGNED(inp) + k(cnt); --OK
        ELSE
          cnt <= 0;
          h0  <= h0 + a;
          h1  <= h1 + b;
          h2  <= h2 + c;
          h3  <= h3 + d;
          h4  <= h4 + e;
          h5  <= h5 + f;
          h6  <= h6 + g;
          h7  <= h7 + h;
        END IF;
      END IF;
    END IF;

  END PROCESS;


  rr02 <= rotate_right(a, 2);     --DA827999
  rr13 <= rotate_right(a, 13);    --333B504F
  rr22 <= rotate_right(a, 22);    --27999DA8
  s0   <= rr02 XOR rr13 XOR rr22; --CE20B47E

  rr06 <= rotate_right(e, 6);     --FD443949
  rr11 <= rotate_right(e, 11);    --4FEA21CA
  rr25 <= rotate_right (e, 25);   --87293FA8
  s1   <= rr06 XOR rr11 XOR rr25; --3587272B

  --       2A01A605      2808E262      3866A200
  maj  <= (a AND b) XOR (a AND c) XOR (b AND c);  --3A6FE667
  --       1104400C         0E818980
  ch   <= (e AND f) XOR ((NOT e) AND g);   --1F85C98C

  t1n   <= h + s1 + ch;
  t2    <= s0 + maj; --OK


  outp <= STD_LOGIC_VECTOR(h0) &
          STD_LOGIC_VECTOR(h1) &
          STD_LOGIC_VECTOR(h2) &
          STD_LOGIC_VECTOR(h3) &
          STD_LOGIC_VECTOR(h4) &
          STD_LOGIC_VECTOR(h5) &
          STD_LOGIC_VECTOR(h6) &
          STD_LOGIC_VECTOR(h7);

END behavioral;

SHA-256v1/VHDL/extender.vhd
LIBRARY ieee;
USE     ieee.std_logic_1164.ALL;
USE     ieee.numeric_std.ALL;

ENTITY extenderSHA256 IS
  PORT    (clk  : IN  STD_LOGIC;                       --clock
           rst  : IN  STD_LOGIC;                       --reset
           inp  : IN  STD_LOGIC_VECTOR (511 DOWNTO 0); --input
           outp : OUT STD_LOGIC_VECTOR (31 DOWNTO 0);  --output
           cts  : OUT STD_LOGIC);                      --clear to send
END extenderSHA256;

ARCHITECTURE behavioral OF extenderSHA256 IS

  CONSTANT chunk_dim  : INTEGER := 16;                  --chunk dimension (in numero di word - 512 bit)
  CONSTANT word_dim   : INTEGER := 32;                  --word dimension (in numero di bit)
  CONSTANT ext_number : INTEGER := 64;                  --extender number: numero finale di parole in uscita
  CONSTANT ws0        : INTEGER := chunk_dim -15;       --indice di w per il calcolo di s0
  CONSTANT ws1        : INTEGER := chunk_dim -2;        --indice di w per il calcolo di s1
  CONSTANT wf1        : INTEGER := chunk_dim -16;       --indice1 di w per il calcolo di nww
  CONSTANT wf2        : INTEGER := chunk_dim -7;        --indice2 di w per il calcolo di nww
  CONSTANT LST        : BIT     := '1';                 --listen mode
  CONSTANT CMP        : BIT     := '0';                 --compute mode

  SUBTYPE WORD  IS UNSIGNED (word_dim-1 DOWNTO 0);
  TYPE    CHUNK IS ARRAY    (chunk_dim-1 DOWNTO 0) OF WORD;

  SIGNAL mode                   : BIT     := LST;      --modalita': listen o compute
  SIGNAL cnt                    : INTEGER := 0;        --contatore
  SIGNAL w                      : CHUNK;               --16 registri che contengono lo stato corrente. w(0) e' l'output
  SIGNAL s0, s1                 : WORD;                
  SIGNAL rr07, rr17, rr18, rr19 : WORD;
  SIGNAL sr03, sr10             : WORD;
  SIGNAL nww                    : WORD;                --segnale che indica ad ogni ciclo il prossimo w(15)
  
BEGIN

  cts <= '1' WHEN (mode = LST) ELSE 
         '0' WHEN (mode = CMP) ELSE
         'X';

  PROCESS (clk, rst)
  BEGIN
    IF (rst = '1') THEN
      mode <= LST;
      cnt <= 0;
    END IF;

    IF (clk'EVENT AND clk = '1') THEN

      IF (mode = LST) THEN
        mode <= CMP;
        FOR i IN 0 TO chunk_dim-1 LOOP
          w(i) <= UNSIGNED(inp (word_dim * (chunk_dim - i)-1 DOWNTO word_dim * (chunk_dim - (i+1))));
        END LOOP;

      ELSIF (mode = CMP) THEN
        IF (cnt <= ext_number-1) THEN
          cnt <= cnt +1;
          outp <= STD_LOGIC_VECTOR(w(0));
          FOR i IN 0 TO chunk_dim-2 LOOP
            w(i) <= w(i+1);
          END LOOP;
          w(chunk_dim-1) <= nww;
        ELSE                            --se ha fatto 64 output azzera il contatore e si mette in modalita' listen
          mode <= LST;
          cnt <= 0;
        END IF;
      END IF;

    END IF;

  END PROCESS;

  --algoritmo per il calcolo del prossimo valore di w(15)
  rr07 <= rotate_right(w(ws0), 7);
  rr18 <= rotate_right(w(ws0), 18);
  sr03 <= shift_right (w(ws0), 3);
  s0   <= rr07 XOR rr18 XOR sr03;

  rr17 <= rotate_right(w(ws1), 17);
  rr19 <= rotate_right(w(ws1), 19);
  sr10 <= shift_right (w(ws1), 10);
  s1   <= rr17 XOR rr19 XOR sr10;
  
  nww <= s0 + s1 + w(wf1) + w(wf2);

END behavioral;

SHA-256v1/VHDL/SHA256.vhd

--https://gist.github.com/hak8or/8794351
--https://calc.penjee.com/
--GAISLER STANDARD https://www.gaisler.com/doc/vhdl2proc.pdf 
--https://gist.github.com/hak8or/8794351
--https://calc.penjee.com/
LIBRARY ieee;
USE     ieee.std_logic_1164.ALL;

--FIND_LEFTMOST

ENTITY SHA256 IS
  PORT    (clk  : IN  STD_LOGIC;
           rst  : IN  STD_LOGIC;
           msgi : IN  STD_LOGIC_VECTOR (511 DOWNTO 0);
           cts  : OUT STD_LOGIC;
           msgo : OUT STD_LOGIC_VECTOR (255 DOWNTO 0));
END SHA256;


ARCHITECTURE structural OF SHA256 IS
  
  COMPONENT extenderSHA256 IS
  PORT    (clk  : IN  STD_LOGIC;                       
           rst  : IN  STD_LOGIC;                       
           inp  : IN  STD_LOGIC_VECTOR (511 DOWNTO 0); 
           outp : OUT STD_LOGIC_VECTOR (31 DOWNTO 0);        
           cts  : OUT STD_LOGIC);                       
  END COMPONENT;

  COMPONENT compressorSHA256 IS
  PORT    (clk  : IN  STD_LOGIC;                       
           rst  : IN  STD_LOGIC;
           enbl : IN  STD_LOGIC;                       
           inp  : IN  STD_LOGIC_VECTOR (31 DOWNTO 0);  
           outp : OUT STD_LOGIC_VECTOR (255 DOWNTO 0));       
  END COMPONENT;

  SIGNAL ext_to_comp : STD_LOGIC_VECTOR (31 DOWNTO 0);
  SIGNAL ctsi, enbli : STD_LOGIC;

BEGIN
  ext256 : extenderSHA256
             PORT MAP (clk => clk,
                       rst => rst,
                       inp => msgi,
                       outp => ext_to_comp,
                       cts  => ctsi);

  comp256 : compressorSHA256
             PORT MAP (clk => clk,
                       rst => rst,
                       enbl => enbli,
                       inp => ext_to_comp,
                       outp => msgo);
  
  cts <= ctsi;  

  PROCESS (clk)
  BEGIN
    IF (clk = '1') THEN
      enbli <= NOT ctsi;
    END IF;
  END PROCESS;

END structural;

SHA-256v1/VHDL/testBench.vhd
LIBRARY ieee;
USE     ieee.std_logic_1164.ALL;
USE     ieee.numeric_std.ALL;

ENTITY testBench IS
END testBench;

ARCHITECTURE structural OF testBench IS

  COMPONENT SHA256
  PORT    (clk  : IN  STD_LOGIC;
           rst  : IN  STD_LOGIC;
           msgi : IN  STD_LOGIC_VECTOR (511 DOWNTO 0);
           cts  : OUT STD_LOGIC;
           msgo : OUT STD_LOGIC_VECTOR (255 DOWNTO 0));
  END COMPONENT;


  COMPONENT vectorGenerator
  PORT (dgst : IN STD_LOGIC_VECTOR (255 DOWNTO 0);
        cts  : IN STD_LOGIC;
        clk  : OUT STD_LOGIC;
        rst  : OUT STD_LOGIC;
        msg  : OUT STD_LOGIC_VECTOR (511 DOWNTO 0));
  END COMPONENT;

  SIGNAL clkTB, rstTB : STD_LOGIC;
  SIGNAL ctsTB        : STD_LOGIC;
  SIGNAL msgTB        : STD_LOGIC_VECTOR (511 DOWNTO 0);
  SIGNAL dgstTB       : STD_LOGIC_VECTOR (255 DOWNTO 0);

BEGIN
  hash : SHA256
           PORT MAP (clk  => clkTB,
                     rst  => rstTB,
                     msgi => msgTB,
                     cts  => ctsTB,
                     msgo => dgstTB);

  vect : vectorGenerator
           PORT MAP (dgst => dgstTB,
                     cts  => ctsTB,
                     clk  => clkTB,
                     rst  => rstTB,
                     msg  => msgTB);
END structural;

SHA-256v1/VCD/testBench.vcd
$date
  Mon Dec 13 20:35:51 2021
$end
$version
  GHDL v0
$end
$timescale
  1 fs
$end
$scope module standard $end
$upscope $end
$scope module std_logic_1164 $end
$upscope $end
$scope module numeric_std $end
$upscope $end
$scope module testbench $end
$var reg 1 ! clktb $end
$var reg 1 " rsttb $end
$var reg 1 # ctstb $end
$var reg 512 $ msgtb[511:0] $end
$var reg 256 % dgsttb[255:0] $end
$scope module hash $end
$var reg 1 & clk $end
$var reg 1 ' rst $end
$var reg 512 ( msgi[511:0] $end
$var reg 1 ) cts $end
$var reg 256 * msgo[255:0] $end
$var reg 32 + ext_to_comp[31:0] $end
$var reg 1 , ctsi $end
$var reg 1 - enbli $end
$scope module ext256 $end
$var reg 1 . clk $end
$var reg 1 / rst $end
$var reg 512 0 inp[511:0] $end
$var reg 32 1 outp[31:0] $end
$var reg 1 2 cts $end
$var reg 1 3 mode $end
$var integer 32 4 cnt $end
$comment w is not handled $end
$var reg 32 5 s0[31:0] $end
$var reg 32 6 s1[31:0] $end
$var reg 32 7 rr07[31:0] $end
$var reg 32 8 rr17[31:0] $end
$var reg 32 9 rr18[31:0] $end
$var reg 32 : rr19[31:0] $end
$var reg 32 ; sr03[31:0] $end
$var reg 32 < sr10[31:0] $end
$var reg 32 = nww[31:0] $end
$upscope $end
$scope module comp256 $end
$var reg 1 > clk $end
$var reg 1 ? rst $end
$var reg 1 @ enbl $end
$var reg 32 A inp[31:0] $end
$var reg 256 B outp[255:0] $end
$var integer 32 C cnt $end
$var reg 32 D h0[31:0] $end
$var reg 32 E a[31:0] $end
$var reg 32 F h1[31:0] $end
$var reg 32 G b[31:0] $end
$var reg 32 H h2[31:0] $end
$var reg 32 I c[31:0] $end
$var reg 32 J h3[31:0] $end
$var reg 32 K d[31:0] $end
$var reg 32 L h4[31:0] $end
$var reg 32 M e[31:0] $end
$var reg 32 N h5[31:0] $end
$var reg 32 O f[31:0] $end
$var reg 32 P h6[31:0] $end
$var reg 32 Q g[31:0] $end
$var reg 32 R h7[31:0] $end
$var reg 32 S h[31:0] $end
$var reg 32 T s0[31:0] $end
$var reg 32 U s1[31:0] $end
$var reg 32 V maj[31:0] $end
$var reg 32 W t1n[31:0] $end
$var reg 32 X t2[31:0] $end
$var reg 32 Y ch[31:0] $end
$var reg 32 Z rr02[31:0] $end
$var reg 32 [ rr06[31:0] $end
$var reg 32 \ rr11[31:0] $end
$var reg 32 ] rr13[31:0] $end
$var reg 32 ^ rr22[31:0] $end
$var reg 32 _ rr25[31:0] $end
$upscope $end
$upscope $end
$scope module vect $end
$var reg 256 ` dgst[255:0] $end
$var reg 1 a cts $end
$var reg 1 b clk $end
$var reg 1 c rst $end
$var reg 512 d msg[511:0] $end
$var reg 1 e iclk $end
$var reg 1 f irst $end
$upscope $end
$upscope $end
$enddefinitions $end
#0
0!
0"
1#
b10000000000000000000000000000000000000000000000000000000000000000000000000000000000000000000000000000000000000000000000000000000000000000000000000000000000000000000000000000000000000000000000000000000000000000000000000000000000000000000000000000000000000000000000000000000000000000000000000000000000000000000000000000000000000000000000000000000000000000000000000000000000000000000000000000000000000000000000000000000000000000000000000000000000000000000000000000000000000000000000000000000000000000000000000000000 $
b0110101000001001111001100110011110111011011001111010111010000101001111000110111011110011011100101010010101001111111101010011101001010001000011100101001001111111100110110000010101101000100011000001111110000011110110011010101101011011111000001100110100011001 %
0&
0'
b10000000000000000000000000000000000000000000000000000000000000000000000000000000000000000000000000000000000000000000000000000000000000000000000000000000000000000000000000000000000000000000000000000000000000000000000000000000000000000000000000000000000000000000000000000000000000000000000000000000000000000000000000000000000000000000000000000000000000000000000000000000000000000000000000000000000000000000000000000000000000000000000000000000000000000000000000000000000000000000000000000000000000000000000000000000 (
1)
b0110101000001001111001100110011110111011011001111010111010000101001111000110111011110011011100101010010101001111111101010011101001010001000011100101001001111111100110110000010101101000100011000001111110000011110110011010101101011011111000001100110100011001 *
bUUUUUUUUUUUUUUUUUUUUUUUUUUUUUUUU +
1,
U-
0.
0/
b10000000000000000000000000000000000000000000000000000000000000000000000000000000000000000000000000000000000000000000000000000000000000000000000000000000000000000000000000000000000000000000000000000000000000000000000000000000000000000000000000000000000000000000000000000000000000000000000000000000000000000000000000000000000000000000000000000000000000000000000000000000000000000000000000000000000000000000000000000000000000000000000000000000000000000000000000000000000000000000000000000000000000000000000000000000 0
bUUUUUUUUUUUUUUUUUUUUUUUUUUUUUUUU 1
12
13
b0 4
bUUUUUUUUUUUUUUUUUUUUUUUUUUUUUUUU 5
bUUUUUUUUUUUUUUUUUUUUUUUUUUUUUUUU 6
bUUUUUUUUUUUUUUUUUUUUUUUUUUUUUUUU 7
bUUUUUUUUUUUUUUUUUUUUUUUUUUUUUUUU 8
bUUUUUUUUUUUUUUUUUUUUUUUUUUUUUUUU 9
bUUUUUUUUUUUUUUUUUUUUUUUUUUUUUUUU :
b000UUUUUUUUUUUUUUUUUUUUUUUUUUUUU ;
b0000000000UUUUUUUUUUUUUUUUUUUUUU <
bXXXXXXXXXXXXXXXXXXXXXXXXXXXXXXXX =
0>
0?
U@
bUUUUUUUUUUUUUUUUUUUUUUUUUUUUUUUU A
b0110101000001001111001100110011110111011011001111010111010000101001111000110111011110011011100101010010101001111111101010011101001010001000011100101001001111111100110110000010101101000100011000001111110000011110110011010101101011011111000001100110100011001 B
b0 C
b01101010000010011110011001100111 D
b01101010000010011110011001100111 E
b10111011011001111010111010000101 F
b10111011011001111010111010000101 G
b00111100011011101111001101110010 H
b00111100011011101111001101110010 I
b10100101010011111111010100111010 J
b10100101010011111111010100111010 K
b01010001000011100101001001111111 L
b01010001000011100101001001111111 M
b10011011000001010110100010001100 N
b10011011000001010110100010001100 O
b00011111100000111101100110101011 P
b00011111100000111101100110101011 Q
b01011011111000001100110100011001 R
b01011011111000001100110100011001 S
b11001110001000001011010001111110 T
b00110101100001110010011100101011 U
b00111010011011111110011001100111 V
b10110000111011011011110111010000 W
b00001000100100001001101011100101 X
b00011111100001011100100110001100 Y
b11011010100000100111100110011001 Z
b11111101010001000011100101001001 [
b01001111111010100010000111001010 \
b00110011001110110101000001001111 ]
b00100111100110011001110110101000 ^
b10000111001010010011111110101000 _
b0110101000001001111001100110011110111011011001111010111010000101001111000110111011110011011100101010010101001111111101010011101001010001000011100101001001111111100110110000010101101000100011000001111110000011110110011010101101011011111000001100110100011001 `
1a
0b
0c
b10000000000000000000000000000000000000000000000000000000000000000000000000000000000000000000000000000000000000000000000000000000000000000000000000000000000000000000000000000000000000000000000000000000000000000000000000000000000000000000000000000000000000000000000000000000000000000000000000000000000000000000000000000000000000000000000000000000000000000000000000000000000000000000000000000000000000000000000000000000000000000000000000000000000000000000000000000000000000000000000000000000000000000000000000000000 d
0e
0f
#5000000
1!
0#
1&
0)
0,
0-
1.
02
03
b00000000000000000000000000000000 5
b00000000000000000000000000000000 6
b00000000000000000000000000000000 7
b00000000000000000000000000000000 8
b00000000000000000000000000000000 9
b00000000000000000000000000000000 :
b00000000000000000000000000000000 ;
b00000000000000000000000000000000 <
b10000000000000000000000000000000 =
1>
0@
0a
1b
1e
#10000000
0!
0&
0.
0>
0b
0e
#15000000
1!
1&
b10000000000000000000000000000000 +
1-
1.
b10000000000000000000000000000000 1
b1 4
b00000000000000000000000000000000 =
1>
1@
b10000000000000000000000000000000 A
1b
1e
#20000000
0!
0&
0.
0>
0b
0e
#25000000
1!
1&
b00000000000000000000000000000000 +
1.
b00000000000000000000000000000000 1
b10 4
b00000000001000000101000000000000 6
b00000000000000000100000000000000 8
b00000000000000000001000000000000 :
b00000000001000000000000000000000 <
b00000000001000000101000000000000 =
1>
b00000000000000000000000000000000 A
b1 C
b01111100000010001000100001001101 E
b01101010000010011110011001100111 G
b10111011011001111010111010000101 I
b00111100011011101111001101110010 K
b00011000110001111110001010100010 M
b01010001000011100101001001111111 O
b10011011000001010110100010001100 Q
b00011111100000111101100110101011 S
b00111111010010001111011110100111 T
b10111111110100010101011001111010 U
b01111010000010011010111001000101 V
b01110010010110110111101001010011 W
b10111001010100101010010111101100 X
b10010011000001100100101000101110 Y
b01011111000000100010001000010011 Z
b10001000011000110001111110001010 [
b01010100010000110001100011111100 \
b01000010011010111110000001000100 ]
b00100010001000010011010111110000 ^
b01100011111100010101000100001100 _
1b
1e
#30000000
0!
0&
0.
0>
0b
0e
#35000000
1!
1&
1.
b11 4
b00000000000000000000000000000000 6
b00000000000000000000000000000000 8
b00000000000000000000000000000000 :
b00000000000000000000000000000000 <
b00000000000000000000000000000000 =
1>
b10 C
b10011100111001010110010011010000 E
b01111100000010001000100001001101 G
b01101010000010011110011001100111 I
b10111011011001111010111010000101 K
b00100000000000011011001001010110 M
b00011000110001111110001010100010 O
b01010001000011100101001001111111 Q
b10011011000001010110100010001100 S
b10010100001011101111110001101100 T
b00010010100111010010110111101111 U
b01111100000010011110010001000101 V
b11111110101100100111100010100110 W
b00010000001110001110000010110001 X
b01010001000011111110001000101011 Y
b00100111001110010101100100110100 Z
b01011000100000000000011011001001 [
b01001010110001000000000000110110 \
b00100110100001001110011100101011 ]
b10010101100100110100001001110011 ^
b00000000110110010010101100010000 _
1b
1e
#40000000
0!
0&
0.
0>
0b
0e
#45000000
1!
1&
1.
b100 4
b00100010000000000000100000000000 6
b00101000000000000000000000010000 8
b00001010000000000000000000000100 :
b00000000000000000000100000010100 <
b00100010000000000000100000000000 =
1>
b11 C
b11000100101011000101010100100110 E
b10011100111001010110010011010000 G
b01111100000010001000100001001101 I
b01101010000010011110011001100111 K
b01101111110110110010001011111010 M
b00100000000000011011001001010110 O
b00011000110001111110001010100010 Q
b01010001000011100101001001111111 S
b10101001010010011010101100111001 T
b01011011011000111110101011011000 U
b11011100101011000100010001000100 V
b11011100011110000001111110101001 W
b10000101111101011110111101111101 X
b00110000000001011110001001010010 Y
b10110001001010110001010101001001 Z
b11101001101111110110110010001011 [
b01011111010011011111101101100100 \
b10101001001101100010010101100010 ]
b10110001010101001001101100010010 ^
b11101101100100010111110100110111 _
1b
1e
#50000000
0!
0&
0.
0>
0b
0e
#55000000
1!
1&
1.
b101 4
b00000000000000000000000000000000 6
b00000000000000000000000000000000 8
b00000000000000000000000000000000 :
b00000000000000000000000000000000 <
b00000000000000000000000000000000 =
1>
b100 C
b01001100001000111110101011001011 E
b11000100101011000101010100100110 G
b10011100111001010110010011010000 I
b01111100000010001000100001001101 K
b00110000001101111110000110110101 M
b01101111110110110010001011111010 O
b00100000000000011011001001010110 Q
b00011000110001111110001010100010 S
b00001010111110011011011010011101 T
b11111001100101100000001111100010 U
b11001100101001010110010011000010 V
b00110010011100010001100101110110 W
b11010111100111110001101101011111 X
b00100000000100110011001011110010 Y
b11010011000010001111101010110010 Z
b11010100110000001101111110000110 [
b00110110101001100000011011111100 \
b01010110010110100110000100011111 ]
b10001111101010110010110100110000 ^
b00011011111100001101101010011000 _
1b
1e
#60000000
0!
0&
0.
0>
0b
0e
#65000000
1!
1&
1.
b110 4
b00000101000010001001010101000010 6
b00000100000000000001000100000000 8
b00000001000000000000010001000000 :
b00000000000010001000000000000010 <
b00000101000010001001010101000010 =
1>
b101 C
b01000011011001101111011100110000 E
b01001100001000111110101011001011 G
b11000100101011000101010100100110 I
b10011100111001010110010011010000 K
b11100111110100000110010000011110 M
b00110000001101111110000110110101 O
b01101111110110110010001011111010 Q
b00100000000000011011001001010110 S
b00110010100001110110011111110110 T
b00010000011100011011010011101111 U
b01000100001001101111011100100010 V
b01011000100011101100101000111001 W
b01110110101011100101111100011000 X
b00101000000110110110001011110100 Y
b00010000110110011011110111001100 Z
b01111011100111110100000110010000 [
b10000011110111001111101000001100 \
b10111001100000100001101100110111 ]
b10011011110111001100000100001101 ^
b11101000001100100000111101110011 _
1b
1e
#70000000
0!
0&
0.
0>
0b
0e
#75000000
1!
1&
1.
b111 4
b00000000000000000000000000000000 6
b00000000000000000000000000000000 8
b00000000000000000000000000000000 :
b00000000000000000000000000000000 <
b10000000000000000000000000000000 =
1>
b110 C
b00101001001011100011101101000010 E
b01000011011001101111011100110000 G
b01001100001000111110101011001011 I
b11000100101011000101010100100110 K
b01001111011001010100000011111010 M
b11100111110100000110010000011110 O
b00110000001101111110000110110101 Q
b01101111110110110010001011111010 S
b11101000101101111100111100000101 T
b01000100110101000000010010001100 U
b01001001001001101111101101000010 V
b00101100000000100000100010100101 W
b00110001110111101100101001000111 X
b01110111010100101110000100011111 Y
b10001010010010111000111011010000 Z
b11101001001111011001010100000011 [
b00011111010010011110110010101000 \
b11011010000100010100100101110001 ]
b10111000111011010000100010100100 ^
b10110010101000000111110100100111 _
1b
1e
#80000000
0!
0&
0.
0>
0b
0e
#85000000
1!
1&
1.
b1000 4
b01011000000010000000000000000000 6
b01001010101000010000001010000100 8
b00010010101010000100000010100001 :
b00000000000000010100001000100101 <
b01011000000010000000000000000000 =
1>
b111 C
b11110000001000000101010110010000 E
b00101001001011100011101101000010 G
b01000011011001101111011100110000 I
b01001100001000111110101011001011 K
b10000010111011011110000001101111 M
b01001111011001010100000011111010 O
b11100111110100000110010000011110 Q
b00110000001101111110000110110101 S
b00010001110110011101011110100110 T
b11000101000010111101110111111100 U
b01100001001001100111011100010000 V
b01011100101110010000010000101011 W
b01110011000000000100111010110110 X
b01100111011101010100010001111010 Y
b00111100000010000001010101100100 Z
b10111110000010111011011110000001 [
b00001101111100000101110110111100 \
b10101100100001111000000100000010 ]
b10000001010101100100001111000000 ^
b01110110111100000011011111000001 _
1b
1e
#90000000
0!
0&
0.
0>
0b
0e
#95000000
1!
1&
1.
b1001 4
b00000000001000000101000000000000 6
b00000000000000000100000000000000 8
b00000000000000000001000000000000 :
b00000000001000000000000000000000 <
b00000000010000001010000000000000 =
1>
b1000 C
b01111010110101011011000110110110 E
b11110000001000000101010110010000 G
b00101001001011100011101101000010 I
b01000011011001101111011100110000 K
b01010011111110010100110111001011 M
b10000010111011011110000001101111 O
b01001111011001010100000011111010 Q
b11100111110100000110010000011110 S
b01000101110000000110001100101011 T
b01101000100000110111111110110111 U
b01111000001001000011000110010010 V
b01011111010000010010010001010000 W
b10111101111001001001010010111101 X
b00001110111011010100000001111011 Y
b10011110101101010110110001101101 Z
b00101101010011111110010100110111 [
b10111001011010100111111100101001 \
b10001101101100111101011010101101 ]
b01010110110001101101100111101011 ^
b11111100101001101110010110101001 _
1b
1e
#100000000
0!
0&
0.
0>
0b
0e
#105000000
1!
1&
1.
b1010 4
b00000000000101100010010100000101 6
b00000000000000000010110000000100 8
b00000000000000000000101100000001 :
b00000000000101100000001000000000 <
b00000000000101100010010100000101 =
1>
b1001 C
b11110101001011010110001110100101 E
b01111010110101011011000110110110 G
b11110000001000000101010110010000 I
b00101001001011100011101101000010 K
b01111010101011111100011000011000 M
b01010011111110010100110111001011 O
b10000010111011011110000001101111 Q
b01001111011001010100000011111010 S
b11010101111010100110011001010110 T
b11110101000001101110011011011101 U
b11110000001001010111000110110100 V
b00010111010101011000110001000110 W
b11000110000011111101100000001010 X
b11010010111010010110010001101111 Y
b01111101010010110101100011101001 Z
b01100001111010101011111100011000 [
b11000011000011110101010111111000 \
b00011101001011111010100101101011 ]
b10110101100011101001011111010100 ^
b01010111111000110000110000111101 _
1b
1e
#110000000
0!
0&
0.
0>
0b
0e
#115000000
1!
1&
1.
b1011 4
b01000100000000000001000000000000 6
b01010000000000000000000000100000 8
b00010100000000000000000000001000 :
b00000000000000000001000000101000 <
b01100110000000000001100000000000 =
1>
b1010 C
b11101111111010001011111101010001 E
b11110101001011010110001110100101 G
b01111010110101011011000110110110 I
b11110000001000000101010110010000 K
b01010011000001110010001010001001 M
b01111010101011111100011000011000 O
b01010011111110010100110111001011 Q
b10000010111011011110000001101111 S
b00100011100010000001011100101110 T
b11110111111101110011100011000111 U
b11111111111011011011001110110101 V
b11001101111001000110100010000000 W
b00100011011101011100101011100011 X
b01010010111111110100111101001010 Y
b01111011111110100010111111010100 Z
b00100101010011000001110010001010 [
b01010001001010100110000011100100 \
b11111010100011110111111101000101 ]
b10100010111111010100011110111111 ^
b10000011100100010100010010101001 _
1b
1e
#120000000
0!
0&
0.
0>
0b
0e
